lifecycles/__init__.py
lifecycles/algorithms/__init__.py
lifecycles/algorithms/classic_match.py
lifecycles/algorithms/event_analysis.py
lifecycles/algorithms/measures.py
lifecycles/classes/__init__.py
lifecycles/classes/classes.py
lifecycles/utils/__init__.py
lifecycles/utils/utils.py
lifecycles/validation/__init__.py
lifecycles/validation/validation.py
lifecycles/viz/__init__.py
lifecycles/viz/viz.py
lifecycles-0.0.1.dist-info/LICENSE
lifecycles-0.0.1.dist-info/METADATA
lifecycles-0.0.1.dist-info/WHEEL
lifecycles-0.0.1.dist-info/top_level.txt
lifecycles-0.0.1.dist-info/RECORD
