Metadata-Version: 2.1
Name: lifecycles
Version: 0.0.1
Summary: Package to analyze the temporal dynamics of (groups of) entities/nodes
Home-page: https://github.com/andreafailla/lifecycles
Author: Andrea Failla
Author-email: andrea.failla@phd.unipi.it
Keywords: clusters communities analysis
Classifier: Development Status :: 4 - Beta
Classifier: Intended Audience :: Developers
Classifier: Topic :: Software Development :: Build Tools
Classifier: License :: OSI Approved :: GNU General Public License v3 or later (GPLv3+)
Classifier: Operating System :: OS Independent
Classifier: Programming Language :: Python
Classifier: Programming Language :: Python :: 3
License-File: LICENSE
Requires-Dist: matplotlib
Requires-Dist: pandas
Requires-Dist: plotly
Requires-Dist: seaborn
Requires-Dist: numpy
Requires-Dist: scipy
Provides-Extra: flag
